{
  "name": "Rajče Dafne",
  "harvestTime": "Červenec-Září",
  "sowingTime": "Březen-Duben",
  "information": "Jedná se o ranou až středně ranou tyčkovou odrůdu rajčat, která je určená hlavně k pěstování ve sklenících či fóliovnících. Venku ji lze pěstovat pouze v teplejších oblastech. Plodí větší rajčata o hmotnosti 120 až 140 g, která jsou odolná vůči popraskání a lze je dobře skladovat. Plody dozrávají do tmavě červené barvy. Rajčata jsou vhodná k přímé konzumaci a k dalšímu běžnému zpracování.",
  "picture": "/pictures/Dafne.png",
  "id": "4a7271dd93161439cd8f1dedd101bb9c"
}
